talc/client/__init__.py
talc/client/api.py
talc/client/cli.py
talc/client/debug.py
talc/client/files.py
talc/client/shared/__init__.py
talc/client/vscode.py
talc-0.2.2.dist-info/METADATA
talc-0.2.2.dist-info/WHEEL
talc-0.2.2.dist-info/entry_points.txt
talc-0.2.2.dist-info/RECORD
